ankiappaaron/__init__.py
ankiappaaron/__main__.py
ankiappaaron-0.0.1.dist-info/LICENSE.txt
ankiappaaron-0.0.1.dist-info/METADATA
ankiappaaron-0.0.1.dist-info/WHEEL
ankiappaaron-0.0.1.dist-info/top_level.txt
ankiappaaron-0.0.1.dist-info/RECORD
