Metadata-Version: 2.1
Name: ankiappaaron
Version: 0.0.1
Summary: Utilities for AnkiApp
Author-email: Aaron Alphabet <aaron.alphabet@posteo.org>
License: Copyright 2023 Aaron Alphabet
Requires-Python: >=3.10
License-File: LICENSE.txt
